primer_io/__init__.py
primer_io-0.1.1.dist-info/WHEEL
primer_io-0.1.1.dist-info/METADATA
primer_io-0.1.1.dist-info/RECORD
